cellcount.py
cellcount-0.0.2.dist-info/LICENSE.txt.txt
cellcount-0.0.2.dist-info/METADATA
cellcount-0.0.2.dist-info/WHEEL
cellcount-0.0.2.dist-info/top_level.txt
cellcount-0.0.2.dist-info/RECORD
