Metadata-Version: 2.1
Name: cellcount
Version: 0.0.2
Summary: Count the number of contiguous regions in a binary array
Home-page: https://github.com/ronan-pickell/cell-count
Author: Ronan Pickell
Author-email: ronanpickell@gmail.com
License: UNKNOWN
Platform: UNKNOWN
Classifier: Programming Language :: Python :: 3.8
Classifier: Programming Language :: Python :: 3.9
Classifier: Programming Language :: Python :: 3.10
Classifier: License :: OSI Approved :: MIT License
Classifier: Operating System :: OS Independent
Classifier: Natural Language :: English
License-File: LICENSE.txt.txt
Requires-Dist: numpy (~=1.19)
